[{
  "_id": {
    "$oid": "67dae96fd560a928cac8dc2c"
  },
  "provinces": {
    "province": "湖南省",
    "universities": [
      "湘潭大学",
      "吉首大学",
      "湖南大学",
      "中南大学",
      "湖南科技大学",
      "长沙理工大学",
      "湖南农业大学",
      "中南林业科技大学",
      "湖南中医药大学",
      "湖南师范大学",
      "湖南理工学院",
      "湘南学院",
      "衡阳师范学院",
      "邵阳学院",
      "怀化学院",
      "湖南文理学院",
      "湖南科技学院",
      "湖南人文科技学院",
      "湖南商学院",
      "南华大学",
      "长沙医学院",
      "长沙学院",
      "湖南工程学院",
      "湖南城市学院",
      "湖南工学院",
      "湖南财政经济学院",
      "湖南警察学院",
      "湖南工业大学",
      "湖南女子学院",
      "湖南第一师范学院",
      "湖南医药学院",
      "长沙师范学院",
      "湖南应用技术学院",
      "湖南信息学院",
      "湖南交通工程学院"
    ]
  },
  "985_211": [
    {
      "university": "湖南大学",
      "is985": true,
      "is211": true
    },
    {
      "university": "中南大学",
      "is985": true,
      "is211": true
    },
    {
      "university": "湖南师范大学",
      "is985": false,
      "is211": true
    }
  ],
  "normal_schools": [
    {
      "university": "湖南师范大学",
      "isNormal": true
    },
    {
      "university": "衡阳师范学院",
      "isNormal": true
    },
    {
      "university": "湖南第一师范学院",
      "isNormal": true
    },
    {
      "university": "长沙师范学院",
      "isNormal": true
    }
  ]
},
{
  "_id": {
    "$oid": "67dae993d560a928cac8dc2d"
  },
  "provinces": {
    "province": "上海",
    "universities": [
      "复旦大学",
      "上海交通大学",
      "同济大学",
      "华东师大",
      "上海财经大学",
      "华东理工",
      "东华大学",
      "上海理工",
      "上海大学",
      "上海外国语大学",
      "上海海洋大学",
      "上海中医药",
      "上海师大",
      "上海政法",
      "上海电机",
      "上海第二工业大学",
      "上海应用技术学院",
      "上海电力",
      "上海外贸",
      "上海金融",
      "上海立信会计学院",
      "上海体育学院",
      "上海音乐学院",
      "上海戏剧学院",
      "杉达学院",
      "华东政法大学",
      "第二军医大学",
      "上海纽约大学",
      "上海科技大学",
      "上海交通大学医学院",
      "上海视觉艺术学院",
      "复旦大学上海医学院",
      "上海海关学院"
    ]
  },
  "985_211": [
    {
      "university": "复旦大学",
      "is985": true,
      "is211": true
    },
    {
      "university": "上海交通大学",
      "is985": true,
      "is211": true
    },
    {
      "university": "同济大学",
      "is985": true,
      "is211": true
    },
    {
      "university": "华东师大",
      "is985": true,
      "is211": true
    },
    {
      "university": "上海财经大学",
      "is985": false,
      "is211": true
    },
    {
      "university": "华东理工",
      "is985": false,
      "is211": true
    },
    {
      "university": "东华大学",
      "is985": false,
      "is211": true
    },
    {
      "university": "上海大学",
      "is985": false,
      "is211": true
    },
    {
      "university": "上海外国语大学",
      "is985": false,
      "is211": true
    },
    {
      "university": "上海海洋大学",
      "is985": false,
      "is211": true
    },
    {
      "university": "上海中医药",
      "is985": false,
      "is211": true
    },
    {
      "university": "第二军医大学",
      "is985": false,
      "is211": true
    }
  ],
  "normal_schools": [
    {
      "university": "华东师大",
      "isNormal": true
    },
    {
      "university": "上海师大",
      "isNormal": true
    }
  ]
},
{
  "_id": {
    "$oid": "67dae9c5d560a928cac8dc2e"
  },
  "provinces": {
    "province": "北京",
    "universities": [
      "清华大学",
      "北京大学",
      "中国人民大学",
      "北京航空航天大学",
      "北京邮电大学",
      "北京师范大学",
      "中国传媒大学",
      "北京语言大学",
      "北京科技大学",
      "中国农业大学",
      "北京理工大学",
      "北京林业大学",
      "北京交通大学",
      "中国矿业大学（北京）",
      "北京信息科技大学",
      "北京工业大学",
      "北京化工大学",
      "中国政法大学",
      "对外经贸大学",
      "中央民族大学",
      "中国地质大学（北京）",
      "中国科学院大学",
      "北京中医药大学",
      "首都经济贸易大学",
      "中央财经大学",
      "北方工业大学",
      "中国石油大学（北京）",
      "外交学院",
      "首都师范大学",
      "中央戏剧学院",
      "中国青年政治学院",
      "北京外国语大学",
      "华北电力大学（北京）",
      "中国人民公安大学",
      "北京协和医学院",
      "北京体育大学",
      "北京工商大学",
      "北京联合大学",
      "首都医科大学",
      "国际关系学院",
      "中央美术学院",
      "北京电子科技学院",
      "中国劳动关系学院",
      "中华女子学院",
      "北京建筑大学",
      "北京印刷学院",
      "北京石油化工学院",
      "首钢工学院",
      "北京农学院",
      "首都体育学院",
      "北京第二外国语学院",
      "北京物资学院",
      "北京警察学院",
      "中央音乐学院",
      "中国戏曲学院",
      "北京舞蹈学院",
      "北京城市学院",
      "北京电影学院",
      "北京服装学院",
      "北京大学医学部",
      "北京政法职业学院",
      "北京信息职业技术学院",
      "北京现代职业技术学院",
      "北京戏曲艺术职业学院",
      "北京培黎职业学院",
      "北京农业职业学院",
      "北京科技职业学院",
      "北京科技经营管理学院",
      "北京经贸职业学院",
      "北京经济技术职业学院",
      "北京京北职业技术学院",
      "北京交通职业技术学院",
      "北京吉利大学",
      "北京汇佳职业学院",
      "北京工业职业技术学院",
      "北京工商管理专修学院",
      "北京电子科技职业学院",
      "北京财贸职业学院",
      "北京北大方正软件技术学院",
      "北大资源美术学院",
      "北京人文大学",
      "北京高等秘书学院",
      "北京应用技术大学",
      "中国防卫科技学院",
      "中国音乐学院",
      "中国信息大学",
      "北京青年政治学院",
      "北京财经专修学院",
      "北京经济管理职业学院",
      "北京美国英语语言学院",
      "中国管理软件学院",
      "财政部财政科学研究所",
      "北大资源学院",
      "现代管理大学",
      "北京民族大学",
      "北京市劳动保障职业学院",
      "北京市建设职工大学",
      "北京市房地产职工大学",
      "北京市汽车工业总公司职工大学",
      "北京市西城经济科学大学",
      "北京市丰台区职工大学",
      "北京广播电视大学",
      "北京教育学院",
      "北京市东城区职工业余大学",
      "北京市总工会职工大学",
      "北京市海淀区职工大学",
      "北京市崇文区职工大学",
      "北京宣武红旗业余大学",
      "北京市石景山区业余大学",
      "北京市朝阳区职工大学",
      "北京市机械工业局职工大学",
      "北京医药集团职工大学",
      "北京劳动保障职业学院",
      "北京社会管理职业学院",
      "中南海业余大学",
      "北京演艺专修学院",
      "北京兴华大学",
      "北京新园明职业学院",
      "中央党校研究生院",
      "中国社科院",
      "北京旅游专修学院",
      "东方文化艺术学院",
      "首都联合职工大学",
      "中国农业科学院",
      "北京影视研修学院",
      "国家法官学院",
      "北京建设大学",
      "北京金融学院",
      "北京黄埔大学",
      "中瑞酒店管理学院",
      "中国建筑设计研究院",
      "北京文理研修学院",
      "北京当代艺术学院",
      "北京大学国际法学院",
      "北京交通运输职业学院",
      "中国艺术研究院",
      "北京工业大学通州分校",
      "北京八维研修学院",
      "中央党校继续教育学院",
      "中央广播电视大学",
      "门头沟区委党校",
      "电信科学技术研究院",
      "首都经济贸易大学密云分校",
      "北京有色金属研究总院研究生部",
      "国家行政学院",
      "北京交通管理干部学院",
      "中共北京市委党校（北京行政学院）",
      "中国疾病预防控制中心",
      "中国舰船研究院",
      "空军指挥学院",
      "北京大学国家发展研究院",
      "解放军医学院",
      "中国社会科学院研究生院",
      "中国铁道科学研究院",
      "中国人民大学继续教育学院",
      "北京市环境保护科学研究院",
      "北京科技大学延庆分校",
      "朝阳二外",
      "中北国际演艺学校"
    ]
  },
  "985_211": [
    {
      "university": "清华大学",
      "is985": true,
      "is211": true
    },
    {
      "university": "北京大学",
      "is985": true,
      "is211": true
    },
    {
      "university": "中国人民大学",
      "is985": true,
      "is211": true
    },
    {
      "university": "北京航空航天大学",
      "is985": true,
      "is211": true
    },
    {
      "university": "北京师范大学",
      "is985": true,
      "is211": true
    },
    {
      "university": "中国农业大学",
      "is985": true,
      "is211": true
    },
    {
      "university": "北京理工大学",
      "is985": true,
      "is211": true
    },
    {
      "university": "北京交通大学",
      "is985": false,
      "is211": true
    },
    {
      "university": "北京科技大学",
      "is985": false,
      "is211": true
    },
    {
      "university": "北京化工大学",
      "is985": false,
      "is211": true
    },
    {
      "university": "北京林业大学",
      "is985": false,
      "is211": true
    },
    {
      "university": "中国矿业大学（北京）",
      "is985": false,
      "is211": true
    },
    {
      "university": "中国地质大学（北京）",
      "is985": false,
      "is211": true
    },
    {
      "university": "北京中医药大学",
      "is985": false,
      "is211": true
    },
    {
      "university": "北京外国语大学",
      "is985": false,
      "is211": true
    },
    {
      "university": "对外经贸大学",
      "is985": false,
      "is211": true
    },
    {
      "university": "中央财经大学",
      "is985": false,
      "is211": true
    },
    {
      "university": "华北电力大学（北京）",
      "is985": false,
      "is211": true
    },
    {
      "university": "中国政法大学",
      "is985": false,
      "is211": true
    },
    {
      "university": "中央民族大学",
      "is985": true,
      "is211": true
    },
    {
      "university": "北京体育大学",
      "is985": false,
      "is211": true
    }
  ],
  "normal_schools": [
    {
      "university": "北京师范大学",
      "isNormal": true
    },
    {
      "university": "首都师范大学",
      "isNormal": true
    }
  ]
},
{
  "_id": {
    "$oid": "67daea74d560a928cac8dc3d"
  },
  "provinces": {
    "province": "黑龙江",
    "universities": [
      "哈尔滨工业大学",
      "哈尔滨工程大学",
      "东北林大",
      "东北农业大学",
      "哈尔滨医科大学",
      "黑龙江科技大学",
      "哈尔滨学院",
      "黑龙江大学",
      "哈尔滨商业大学",
      "哈尔滨师范大学",
      "哈尔滨理工大学",
      "哈尔滨医科大学(大庆)",
      "佳木斯大学",
      "齐齐哈尔大学",
      "齐齐哈尔医学院",
      "黑龙江八一农垦大学",
      "东北石油大学",
      "大庆师范学院",
      "牡丹江医学院",
      "牡丹江师范",
      "绥化学院",
      "黑河学院",
      "哈尔滨信息工程学院",
      "哈尔滨金融学院",
      "黑龙江中医药大学",
      "哈尔滨远东理工学院",
      "黑龙江外国语学院",
      "哈尔滨石油学院",
      "东北农业大学成栋学院",
      "黑龙江大学剑桥学院",
      "哈尔滨广厦学院",
      "哈尔滨华德学院",
      "黑龙江财经学院",
      "哈理工荣成校区"
    ]
  },
  "985_211": [
    {
      "university": "哈尔滨工业大学",
      "is985": true,
      "is211": true
    },
    {
      "university": "东北农业大学",
      "is985": false,
      "is211": true
    },
    {
      "university": "东北林大",
      "is985": false,
      "is211": true
    }
  ],
  "normal_schools": [
    {
      "university": "哈尔滨师范大学",
      "isNormal": true
    }
  ]
},
{
  "_id": {
    "$oid": "67daea91d560a928cac8dc3e"
  },
  "provinces": {
    "province": "吉林",
    "universities": [
      "吉林大学",
      "东北师范大学",
      "长春大学",
      "吉林农大",
      "长春中医药",
      "东北电力大学",
      "吉林化工",
      "吉林建筑大学",
      "长春工程学院",
      "长春师范大学",
      "吉林工程师范",
      "吉林华桥外国语学院",
      "吉林财经大学",
      "吉林体院",
      "吉林艺术学院",
      "长春工业大学",
      "长春理工大学",
      "吉林工商学院-西安校区",
      "吉林工商学院-卡伦校区",
      "延边大学",
      "北华大学",
      "吉林农业科技学院",
      "吉林医药学院",
      "吉林师范",
      "白城师范学院",
      "通化师范学院",
      "东北师范大学人文学院",
      "吉林大学—莱姆顿学院",
      "长春光华学院",
      "长春大学旅游学院",
      "长春工业大学人文信息学院",
      "吉林动画学院",
      "长春理工大学光电信息学院",
      "吉林财经大学信息经济学院",
      "长春科技学院",
      "吉林师范大学博达学院",
      "长春建筑学院",
      "吉林建筑大学城建学院",
      "吉林警察学院",
      "吉林大学工商管理学院"
    ]
  },
  "985_211": [
    {
      "university": "吉林大学",
      "is985": true,
      "is211": true
    },
    {
      "university": "东北师范大学",
      "is985": false,
      "is211": true
    },
    {
      "university": "延边大学",
      "is985": false,
      "is211": true
    }
  ],
  "normal_schools": [
    {
      "university": "东北师范大学",
      "isNormal": true
    },
    {
      "university": "长春师范大学",
      "isNormal": true
    },
    {
      "university": "吉林师范",
      "isNormal": true
    },
    {
      "university": "白城师范学院",
      "isNormal": true
    },
    {
      "university": "通化师范学院",
      "isNormal": true
    }
  ]
},
{
  "_id": {
    "$oid": "67daeabad560a928cac8dc3f"
  },
  "provinces": {
    "province": "辽宁",
    "universities": [
      "大连理工",
      "东北大学",
      "辽宁大学",
      "大连海事",
      "东北财经",
      "大连大学",
      "大连交大",
      "大连医大",
      "辽宁师大",
      "大连民族",
      "大连工大",
      "大连海洋大学",
      "大连外国语大学",
      "辽宁外经贸",
      "辽宁科技大学（营口大学园）",
      "大连财经学院",
      "营口理工学院",
      "鲁迅美术学院（大连校区）",
      "沈阳大学",
      "沈阳理工",
      "沈阳工大",
      "沈阳建筑",
      "沈阳农大",
      "辽宁中医药",
      "沈阳药科",
      "沈阳师范大学",
      "中国刑警学院",
      "沈阳化工",
      "沈阳航空航天大学",
      "沈阳工程",
      "沈阳医学院",
      "沈阳体院",
      "沈阳音乐学院",
      "中国医科大",
      "辽宁工程技术大学",
      "辽宁石化",
      "鞍山师范学院",
      "渤海大学",
      "辽宁工业大学",
      "辽宁医学院",
      "辽宁科技学院",
      "辽东学院",
      "大连东软信息学院",
      "辽宁传媒学院",
      "辽宁科技大学",
      "大连科技学院",
      "沈阳城市建设学院",
      "辽宁科技大学信息技术学院",
      "辽宁石油化工大学顺华能源学院",
      "沈阳化工学院科亚学院",
      "沈阳工学院",
      "中国医科大学临床医药学院",
      "大连医科大学中山学院",
      "辽宁医学院医疗学院",
      "辽宁中医药大学杏林学院",
      "辽宁何氏医学院",
      "辽宁师范大学海华学院",
      "大连财经学院",
      "辽宁财贸学院",
      "大连理工大学城市学院",
      "沈阳城市学院",
      "辽宁建筑职业学院",
      "辽宁对外经贸学院",
      "鲁迅美术学院（沈阳校区）",
      "大连艺术学院"
    ]
  },
  "985_211": [
    {
      "university": "大连理工",
      "is985": true,
      "is211": true
    },
    {
      "university": "东北大学",
      "is985": true,
      "is211": true
    },
    {
      "university": "辽宁大学",
      "is985": false,
      "is211": true
    },
    {
      "university": "大连海事",
      "is985": false,
      "is211": true
    }
  ],
  "normal_schools": [
    {
      "university": "辽宁师大",
      "isNormal": true
    },
    {
      "university": "沈阳师范大学",
      "isNormal": true
    },
    {
      "university": "鞍山师范学院",
      "isNormal": true
    }
  ]
},
{
  "_id": {
    "$oid": "67daeae0d560a928cac8dc41"
  },
  "provinces": {
    "province": "天津",
    "universities": [
      "南开大学",
      "天津大学",
      "河北工大",
      "天津师大",
      "天津工大",
      "天津科大",
      "天津理工",
      "天津医大",
      "天津中医药",
      "天津财经大学",
      "中国民航大学",
      "天津城建大学",
      "天津农院",
      "天津外国语",
      "天津商业大学",
      "天津体院",
      "天津音乐学院",
      "天津美院",
      "天津体育学院",
      "天津天狮学院",
      "天津外国语大学滨海外事学院",
      "天津体育学院运动与文化艺术学院",
      "天津商业大学宝德学院",
      "天津医科大学临床医学院",
      "北京科技大学天津学院",
      "天津师范大学津沽学院",
      "天津理工大学中环信息学院",
      "天津大学仁爱学院",
      "天津财经大学珠江学院",
      "南开大学滨海学院",
      "天津职业技术师范大学"
    ]
  },
  "985_211": [
    {
      "university": "南开大学",
      "is985": true,
      "is211": true
    },
    {
      "university": "天津大学",
      "is985": true,
      "is211": true
    },
    {
      "university": "河北工大",
      "is985": false,
      "is211": true
    }
  ],
  "normal_schools": [
    {
      "university": "天津师大",
      "isNormal": true
    },
    {
      "university": "天津职业技术师范大学",
      "isNormal": true
    }
  ]
},
{
  "_id": {
    "$oid": "67daeaf4d560a928cac8dc43"
  },
  "provinces": {
    "province": "安徽",
    "universities": [
      "中国科大",
      "安徽大学",
      "合肥工大",
      "安徽医科大",
      "安徽建筑大学",
      "安徽中医",
      "合肥学院",
      "安徽农大",
      "安徽大学江淮学院",
      "安徽财经大学商学院",
      "安徽工程大学机电学院",
      "安徽工业大学工商学院",
      "安徽建筑工业学院城市建设学院",
      "安徽农业大学经济技术学院",
      "安徽医科大学临床医学院",
      "阜阳师范学院信息工程学院",
      "淮北师范大学信息学院",
      "合肥工业大学宣城校区",
      "安徽大学国际商学院",
      "安徽工业大学",
      "安徽科技",
      "皖南医学院",
      "安徽师大",
      "安徽工程大学",
      "蚌埠医学院",
      "安徽财经",
      "阜阳师范学院",
      "淮南师范",
      "安徽理工大学",
      "淮北师范大学",
      "安庆师范",
      "铜陵学院",
      "皖西学院",
      "巢湖学院",
      "滁州学院",
      "宿州学院",
      "黄山学院",
      "新华学院",
      "蚌埠学院",
      "安徽三联学院",
      "安徽文达信息工程学院",
      "安徽外国语学院",
      "安徽师范大学皖江学院",
      "合肥师范学院",
      "河海大学文天学院",
      "安徽科技学院"
    ]
  },
  "985_211": [
    {
      "university": "中国科大",
      "is985": true,
      "is211": true
    },
    {
      "university": "安徽大学",
      "is985": false,
      "is211": true
    },
    {
      "university": "合肥工大",
      "is985": false,
      "is211": true
    }
  ],
  "normal_schools": [
    {
      "university": "安徽师大",
      "isNormal": true
    },
    {
      "university": "阜阳师范学院",
      "isNormal": true
    },
    {
      "university": "淮南师范",
      "isNormal": true
    },
    {
      "university": "淮北师范大学",
      "isNormal": true
    },
    {
      "university": "安庆师范",
      "isNormal": true
    },
    {
      "university": "合肥师范学院",
      "isNormal": true
    }
  ]
},
{
  "_id": {
    "$oid": "67daeb02d560a928cac8dc45"
  },
  "provinces": {
    "province": "江苏",
    "universities": [
      "南京大学",
      "河海大学",
      "南京师大",
      "南京理工",
      "东南大学",
      "南京航空航天大学",
      "南京财经",
      "南京医科大",
      "南京工业大学",
      "南京农大",
      "南京林业大学",
      "南京邮电大学",
      "南京信息工程大学",
      "南京中医药",
      "南京工程学院",
      "金陵科技学院",
      "南京晓庄学院",
      "南京审计学院",
      "江苏警官学院",
      "南京体院",
      "南京艺术学院",
      "三江学院",
      "中国药科大",
      "江苏理工学院",
      "江苏师范大学",
      "江苏科技大学张家港校区",
      "江苏师范大学连云港校区",
      "苏州大学",
      "南京体育学院奥林匹克学院",
      "江南大学",
      "中国矿业大学",
      "徐州医学院",
      "扬州大学",
      "江苏大学",
      "江苏科大",
      "南通大学",
      "常州大学",
      "常州工学院",
      "淮阴工学院",
      "淮阴师范",
      "淮海工学院",
      "盐城工学院",
      "盐城师范学院",
      "常熟理工",
      "苏州科技大学",
      "宿迁学院",
      "泰州学院",
      "南通理工学院",
      "江苏第二师范学院",
      "徐州工程学院",
      "南京理工大学泰州科技学院",
      "东南大学成贤学院",
      "南京理工大学紫金学院",
      "南京航空航天大学金城学院",
      "南京财经大学红山学院",
      "南京师范大学泰州学院",
      "南京审计学院金审学院",
      "南通大学杏林学院",
      "江苏工业学院怀德学院",
      "江苏科技大学苏州理工学院",
      "南京邮电大学通达学院",
      "徐州师范大学科文学院",
      "扬州大学广陵学院",
      "江苏大学京江学院",
      "苏州科技学院天平学院",
      "苏州大学应用技术学院",
      "苏州大学文正学院",
      "南京信息工程大学滨江学院",
      "南京中医药大学翰林学院",
      "南京医科大学康达学院",
      "南京师范大学中北学院",
      "南京工业大学浦江学院",
      "无锡太湖学院",
      "西交利物浦大学",
      "中国矿业大学徐海学院",
      "南京大学金陵学院"
    ]
  },
  "985_211": [
    {
      "university": "南京大学",
      "is985": true,
      "is211": true
    },
    {
      "university": "东南大学",
      "is985": true,
      "is211": true
    },
    {
      "university": "河海大学",
      "is985": false,
      "is211": true
    },
    {
      "university": "南京师大",
      "is985": false,
      "is211": true
    },
    {
      "university": "南京理工",
      "is985": false,
      "is211": true
    },
    {
      "university": "南京航空航天大学",
      "is985": false,
      "is211": true
    },
    {
      "university": "南京农大",
      "is985": false,
      "is211": true
    },
    {
      "university": "中国药科大",
      "is985": false,
      "is211": true
    },
    {
      "university": "江南大学",
      "is985": false,
      "is211": true
    },
    {
      "university": "中国矿业大学",
      "is985": false,
      "is211": true
    }
  ],
  "normal_schools": [
    {
      "university": "南京师大",
      "isNormal": true
    },
    {
      "university": "江苏师范大学",
      "isNormal": true
    },
    {
      "university": "淮阴师范",
      "isNormal": true
    },
    {
      "university": "江苏第二师范学院",
      "isNormal": true
    }
  ]
},
{
  "_id": {
    "$oid": "67daeb0fd560a928cac8dc47"
  },
  "provinces": {
    "province": "浙江",
    "universities": [
      "浙江大学",
      "浙江理工",
      "浙江工大",
      "杭州电子科大",
      "浙江中医药",
      "浙江工商大学",
      "中国计量",
      "浙江科技",
      "浙江农林大学",
      "杭州师范大学",
      "浙江传媒",
      "浙江财经大学",
      "中国美术学院",
      "树人大学",
      "温州肯恩大学",
      "湖州师范学院求真学院",
      "中国计量学院现代科技学院",
      "浙江财经大学东方学院",
      "浙江农林大学天目学院",
      "浙江海洋学院东海科学技术学院",
      "温州医科大学仁济学院",
      "绍兴文理学院元培学院",
      "温州大学瓯江学院",
      "嘉兴学院南湖学院",
      "温州大学城市学院",
      "杭州电子科技大学信息工程学院",
      "浙江中医药大学滨江学院",
      "浙江工商大学杭州商学院",
      "杭州师范大学美术学院",
      "宁波大学",
      "宁波工程",
      "万里学院",
      "诺丁汉大学",
      "嘉兴学院",
      "浙江海洋",
      "温州大学",
      "温州医科大学",
      "湖州师范学院",
      "台州学院",
      "绍兴文理学院",
      "丽水学院",
      "浙江师大",
      "宁波大红鹰学院",
      "宁波大学科技学院",
      "浙江外国语学院",
      "浙江水利水电学院",
      "衢州学院",
      "同济大学浙江学院",
      "杭州师范大学钱江学院",
      "上海财经大学浙江学院",
      "浙江师范大学行知学院",
      "浙江理工大学科技与艺术学院",
      "浙江工业大学之江学院"
    ]
  },
  "985_211": [
    {
      "university": "浙江大学",
      "is985": true,
      "is211": true
    }
  ],
  "normal_schools": [
    {
      "university": "杭州师范大学",
      "isNormal": true
    },
    {
      "university": "浙江师大",
      "isNormal": true
    }
  ]
},
{
  "_id": {
    "$oid": "67daeb18d560a928cac8dc49"
  },
  "provinces": {
    "province": "陕西",
    "universities": [
      "西安交大",
      "长安大学",
      "西北工大",
      "西北大学",
      "陕西师大",
      "西安电子科大",
      "西安理工",
      "西安科大",
      "西安工大",
      "西安外国语大学",
      "西安邮电大学",
      "西安医学院",
      "西安财经",
      "西北政法",
      "西安体院",
      "西安美院",
      "西安音乐学院",
      "西安文理学院",
      "西京学院",
      "西安翻译学院",
      "培华学院",
      "欧亚学院",
      "西安外事",
      "西安石油",
      "西安建筑科大",
      "第四军医大学",
      "西北工业大学明德学院",
      "长安大学兴华学院",
      "西安航空学院",
      "陕西学前师范学院",
      "延安大学",
      "陕西中医药大学",
      "咸阳师范学院",
      "陕西科大",
      "宝鸡文理学院",
      "渭南师范",
      "陕西理工",
      "榆林学院",
      "商洛学院",
      "安康学院",
      "西北农林科大",
      "陕西服装工程学院",
      "西安工程大学",
      "西安交通工程学院",
      "西安思源学院",
      "西安建筑科技大学华清学院",
      "西安财经学院行知学院",
      "陕西科技大学镐京学院",
      "西安工业大学北方信息工程学院",
      "延安大学西安创新学院",
      "西安电子科技大学长安学院",
      "西安理工大学高科学院",
      "西安科技大学高新学院",
      "西安交通大学城市学院",
      "西北大学现代学院"
    ]
  },
  "985_211": [
    {
      "university": "西安交大",
      "is985": true,
      "is211": true
    },
    {
      "university": "西北工大",
      "is985": true,
      "is211": true
    },
    {
      "university": "长安大学",
      "is985": false,
      "is211": true
    },
    {
      "university": "西北大学",
      "is985": false,
      "is211": true
    },
    {
      "university": "陕西师大",
      "is985": false,
      "is211": true
    },
    {
      "university": "西安电子科大",
      "is985": false,
      "is211": true
    },
    {
      "university": "西北农林科大",
      "is985": true,
      "is211": true
    }
  ],
  "normal_schools": [
    {
      "university": "陕西师大",
      "isNormal": true
    },
    {
      "university": "咸阳师范学院",
      "isNormal": true
    },
    {
      "university": "渭南师范",
      "isNormal": true
    },
    {
      "university": "陕西学前师范学院",
      "isNormal": true
    }
  ]
},
{
  "_id": {
    "$oid": "67daeb23d560a928cac8dc4b"
  },
  "provinces": {
    "province": "湖北",
    "universities": [
      "武汉大学",
      "华中科技大学",
      "华中农大",
      "武汉理工",
      "中国地质大学（武汉）",
      "中南财经政法大学",
      "中南民族大学",
      "华中师大",
      "武汉轻工大学",
      "武汉纺织大学",
      "湖北中医药大学",
      "湖北经济学院",
      "湖北警官学院",
      "武汉体育学院",
      "湖北美院",
      "武汉音乐学院",
      "武汉生物工程学院",
      "湖北工业大学",
      "湖北大学",
      "江汉大学",
      "武汉工大",
      "武汉科大",
      "武汉工程大学",
      "长江大学",
      "三峡大学",
      "湖北汽院",
      "湖北医药学院",
      "湖北工程学院",
      "湖北师范学院",
      "湖北理工学院",
      "黄冈师院",
      "湖北民族学院",
      "湖北文理学院",
      "湖北科技学院",
      "湖北第二师范学院",
      "荆楚理工学院",
      "武汉商学院",
      "郧阳师范高等专科学校",
      "武汉长江工商学院",
      "华中科技大学文华学院",
      "汉口学院",
      "湖北大学知行学院",
      "三峡大学科技学院",
      "武昌理工学院",
      "湖北工业大学工程技术学院",
      "武昌工学院",
      "武汉工程大学邮电与信息工程学院",
      "武汉纺织大学外经贸学院",
      "江汉大学文理学院",
      "湖北汽车工业学院科技学院",
      "湖北经济学院法商学院",
      "武汉体育学院体育科技学院",
      "湖北医药学院药护学院",
      "湖北文理学院理工学院",
      "武汉工程科技学院",
      "长江大学文理学院",
      "长江大学工程技术学院",
      "华中师范大学武汉传媒学院",
      "武汉东湖学院",
      "中南财经政法武汉学院",
      "华中科技大学武昌分校",
      "武汉科技大学城市学院",
      "武汉大学珞珈学院"
    ]
  },
  "985_211": [
    {
      "university": "武汉大学",
      "is985": true,
      "is211": true
    },
    {
      "university": "华中科技大学",
      "is985": true,
      "is211": true
    },
    {
      "university": "华中农大",
      "is985": false,
      "is211": true
    },
    {
      "university": "武汉理工",
      "is985": false,
      "is211": true
    },
    {
      "university": "中国地质大学（武汉）",
      "is985": false,
      "is211": true
    },
    {
      "university": "中南财经政法大学",
      "is985": false,
      "is211": true
    },
    {
      "university": "华中师大",
      "is985": false,
      "is211": true
    }
  ],
  "normal_schools": [
    {
      "university": "华中师大",
      "isNormal": true
    },
    {
      "university": "湖北师范学院",
      "isNormal": true
    },
    {
      "university": "湖北第二师范学院",
      "isNormal": true
    },
    {
      "university": "黄冈师院",
      "isNormal": true
    },
    {
      "university": "郧阳师范高等专科学校",
      "isNormal": true
    }
  ]
},
{
  "_id": {
    "$oid": "67daeb2ed560a928cac8dc4d"
  },
  "provinces": {
    "province": "广东",
    "universities": [
      "华南理工大学",
      "中山大学",
      "暨南大学",
      "华南师范大学",
      "广东工业大学",
      "华南农业大学",
      "广州大学",
      "广东外语外贸大学",
      "广州中医药大学",
      "南方医科大学",
      "南方科技大学",
      "仲恺农业工程学院",
      "广州医科大学",
      "广东药学院",
      "广东金融学院",
      "广东财经大学",
      "广东警官学院",
      "广州体育学院",
      "广州美术学院",
      "星海音乐学院",
      "广东技术师范学院",
      "广东培正学院",
      "广东白云学院",
      "清华大学深圳研究生院",
      "广东理工学院",
      "深圳大学",
      "汕头大学",
      "五邑大学",
      "肇庆学院",
      "广东石油化工学院",
      "东莞理工学院",
      "广东医学院",
      "湛江师范学院",
      "广东海洋大学",
      "韶关学院",
      "韩山师范学院",
      "嘉应学院",
      "惠州学院",
      "佛山科学技术学院",
      "中山大学南方学院",
      "广东外语外贸大学南国商学院",
      "华南理工大学广州学院",
      "北京理工大学珠海学院",
      "北京师范大学珠海分校",
      "电子科技大学中山学院",
      "东莞理工学院城市学院",
      "广东科技学院",
      "广东第二师范学院",
      "广州航海学院",
      "广州大学华软软件学院",
      "广州大学松田学院",
      "华南农业大学珠江学院",
      "华南师范大学增城学院",
      "吉林大学珠海学院",
      "中山大学新华学院",
      "广东商学院华商学院",
      "北京师范大学－香港浸会大学联合国际学院",
      "香港中文大学（深圳）"
    ]
  },
  "985_211": [
    {
      "university": "华南理工大学",
      "is985": true,
      "is211": true
    },
    {
      "university": "中山大学",
      "is985": true,
      "is211": true
    },
    {
      "university": "暨南大学",
      "is985": false,
      "is211": true
    },
    {
      "university": "华南师范大学",
      "is985": false,
      "is211": true
    }
  ],
  "normal_schools": [
    {
      "university": "华南师范大学",
      "isNormal": true
    },
    {
      "university": "湛江师范学院",
      "isNormal": true
    },
    {
      "university": "韩山师范学院",
      "isNormal": true
    },
    {
      "university": "广东第二师范学院",
      "isNormal": true
    }
  ]
},
{
  "_id": {
    "$oid": "67daeb38d560a928cac8dc4f"
  },
  "provinces": {
    "province": "湖南",
    "universities": [
      "湖南师大",
      "中南大学",
      "湖南大学",
      "长沙理工",
      "湖南农大",
      "湖南中医药",
      "中南林业科技大学",
      "长沙学院",
      "长沙医学院",
      "湖南涉外经济学院",
      "湖南商学院",
      "湖南人文科技",
      "国防科学技术大学",
      "湘潭大学",
      "湖南科大",
      "湖南工程学院",
      "南华大学",
      "吉首大学",
      "湖南工大",
      "湖南城市学院",
      "湖南理工学院",
      "湘南学院",
      "衡阳师院",
      "湖南文理",
      "怀化学院",
      "湖南科技学院",
      "邵阳学院",
      "长沙师范学院",
      "湖南财政经济学院",
      "湖南第一师范学院",
      "湖南工学院",
      "湖南女子学院",
      "湖南交通工程学院",
      "湘潭大学兴湘学院",
      "湖南工业大学科技学院",
      "湖南科技大学潇湘学院",
      "南华大学船山学院",
      "湖南商学院北津学院",
      "湖南师范大学树达学院",
      "湖南农业大学东方科技学院",
      "中南林业科技大学涉外学院",
      "湖南文理学院芙蓉学院",
      "湖南理工学院南湖学院",
      "衡阳师范学院南岳学院",
      "湖南工程学院应用技术学院",
      "湖南中医药大学湘杏学院",
      "吉首大学张家界学院",
      "长沙理工大学城南学院"
    ]
  },
  "985_211": [
    {
      "university": "中南大学",
      "is985": true,
      "is211": true
    },
    {
      "university": "湖南大学",
      "is985": true,
      "is211": true
    },
    {
      "university": "湖南师大",
      "is985": false,
      "is211": true
    },
    {
      "university": "国防科学技术大学",
      "is985": true,
      "is211": true
    }
  ],
  "normal_schools": [
    {
      "university": "湖南师大",
      "isNormal": true
    },
    {
      "university": "衡阳师院",
      "isNormal": true
    },
    {
      "university": "长沙师范学院",
      "isNormal": true
    },
    {
      "university": "湖南第一师范学院",
      "isNormal": true
    }
  ]
},
{
  "_id": {
    "$oid": "67daeb46d560a928cac8dc51"
  },
  "provinces": {
    "province": "甘肃",
    "universities": [
      "兰州大学",
      "西北民大",
      "西北师范大学",
      "甘肃中医学院",
      "兰州财经大学",
      "甘肃政法学院",
      "兰州城市学院",
      "甘肃农大",
      "兰州理工",
      "兰州交大",
      "西北师范大学知行学院",
      "天水师院",
      "陇东学院",
      "河西学院",
      "兰州理工大学技术工程学院",
      "甘肃民族师范学院",
      "兰州文理学院",
      "兰州交通大学博文学院",
      "兰州工业学院",
      "兰州商学院长青学院",
      "兰州商学院陇桥学院"
    ]
  },
  "985_211": [
    {
      "university": "兰州大学",
      "is985": true,
      "is211": true
    }
  ],
  "normal_schools": [
    {
      "university": "西北师范大学",
      "isNormal": true
    },
    {
      "university": "西北师范大学知行学院",
      "isNormal": true
    },
    {
      "university": "天水师院",
      "isNormal": true
    },
    {
      "university": "甘肃民族师范学院",
      "isNormal": true
    }
  ]
},
{
  "_id": {
    "$oid": "67daeb4ed560a928cac8dc53"
  },
  "provinces": {
    "province": "四川",
    "universities": [
      "四川大学",
      "四川农大",
      "电子科技大学",
      "西南交通大学",
      "成都理工大学",
      "四川师大",
      "西南民族大学",
      "成都大学",
      "西南财经",
      "西华大学",
      "成都中医药",
      "成都信息工程大学",
      "成都医学院",
      "四川文理学院",
      "成都体育学院",
      "四川艺术大学",
      "西南石油大学",
      "西南交通大学希望学院",
      "四川传媒学院",
      "西南交通大学峨眉校区",
      "中国民航飞行学院",
      "四川理工",
      "泸州医学院",
      "川北医学院",
      "西华师范大学",
      "内江师范",
      "乐山师院",
      "绵阳师范",
      "西南科技大学",
      "西昌学院",
      "宜宾学院",
      "攀枝花学院",
      "阿坝师范高等专科学校",
      "成都工业学院",
      "成都东软学院",
      "成都师范学院",
      "四川旅游学院",
      "四川师范大学绵阳初等教育学院",
      "四川大学锦城学院",
      "四川大学锦江学院",
      "四川师范大学成都学院",
      "四川师范大学文理学院",
      "成都信息工程学院银杏酒店管理学院",
      "成都理工大学工程技术学院",
      "四川文化艺术学院",
      "西南财经大学天府学院",
      "四川民族学院",
      "四川电影电视学院"
    ]
  },
  "985_211": [
    {
      "university": "四川大学",
      "is985": true,
      "is211": true
    },
    {
      "university": "电子科技大学",
      "is985": true,
      "is211": true
    },
    {
      "university": "西南交通大学",
      "is985": false,
      "is211": true
    },
    {
      "university": "四川农大",
      "is985": false,
      "is211": true
    },
    {
      "university": "西南财经",
      "is985": false,
      "is211": true
    }
  ],
  "normal_schools": [
    {
      "university": "四川师大",
      "isNormal": true
    },
    {
      "university": "西华师范大学",
      "isNormal": true
    },
    {
      "university": "绵阳师范",
      "isNormal": true
    },
    {
      "university": "乐山师院",
      "isNormal": true
    },
    {
      "university": "内江师范",
      "isNormal": true
    },
    {
      "university": "阿坝师范高等专科学校",
      "isNormal": true
    },
    {
      "university": "成都师范学院",
      "isNormal": true
    },
    {
      "university": "四川师范大学绵阳初等教育学院",
      "isNormal": true
    }
  ]
},
{
  "_id": {
    "$oid": "67daeb56d560a928cac8dc55"
  },
  "provinces": {
    "province": "山东",
    "universities": [
      "山东大学",
      "中国海洋大学",
      "济南大学",
      "山东建筑大学",
      "山东师大",
      "山东财经大学",
      "山东中医药",
      "齐鲁工业大学",
      "山东交通学院",
      "山东警院",
      "山东体育学院",
      "山东艺术学院",
      "山东工美",
      "曲阜师大",
      "北京电影学院现代创意媒体学院",
      "哈尔滨理工大学（荣成校区）",
      "烟台大学",
      "鲁东大学",
      "山东工商",
      "烟台南山学院",
      "青岛大学",
      "山东科大",
      "青岛科大",
      "青岛理工",
      "青岛农业大学",
      "滨海学院",
      "中国石油大学（华东）",
      "聊城大学",
      "山东理工",
      "潍坊医学院",
      "潍坊学院",
      "泰山医学院",
      "泰山学院",
      "山东农大",
      "滨州医学院",
      "滨州学院",
      "济宁医学院",
      "临沂大学",
      "德州学院",
      "枣庄学院",
      "菏泽学院",
      "济宁学院",
      "山东大学（威海）",
      "山东政法学院",
      "齐鲁师范学院",
      "山东农业工程学院",
      "山东青年政治学院",
      "山东管理学院",
      "中国石油大学胜利学院",
      "烟台大学文经学院",
      "青岛理工大学琴岛学院",
      "山东科技大学泰山科技学院",
      "青岛工学院",
      "山东财经大学燕山学院",
      "青岛农业大学海都学院",
      "齐鲁理工学院（曲阜校区）",
      "山东财经大学东方学院",
      "山东师范大学历山学院",
      "聊城大学东昌学院",
      "济南大学泉城学院",
      "中国农业大学（烟台校区）",
      "山东艺术设计学院",
      "青岛理工大学（临沂）",
      "山东女子学院"
    ]
  },
  "985_211": [
    {
      "university": "山东大学",
      "is985": true,
      "is211": true
    },
    {
      "university": "中国海洋大学",
      "is985": true,
      "is211": true
    },
    {
      "university": "中国石油大学（华东）",
      "is985": false,
      "is211": true
    }
  ],
  "normal_schools": [
    {
      "university": "山东师大",
      "isNormal": true
    },
    {
      "university": "曲阜师大",
      "isNormal": true
    },
    {
      "university": "齐鲁师范学院",
      "isNormal": true
    },
    {
      "university": "山东师范大学历山学院",
      "isNormal": true
    }
  ]
},
{
  "_id": {
    "$oid": "67daeb5dd560a928cac8dc57"
  },
  "provinces": {
    "province": "福建",
    "universities": [
      "厦门大学",
      "集美大学",
      "厦门理工学院",
      "宁德师范学院",
      "福州大学厦门工艺美术学院",
      "福州大学",
      "福建师范大学",
      "福建农林大学",
      "福建医科大学",
      "福建工程学院",
      "福建中医药大学",
      "闽江学院",
      "华侨大学",
      "仰恩大学",
      "泉州师范学院",
      "闽南师范大学",
      "莆田学院",
      "三明学院",
      "龙岩学院",
      "厦门大学嘉庚学院",
      "集美大学诚毅学院",
      "福州大学阳光学院",
      "福州大学至诚学院",
      "福建师范大学协和学院",
      "福建师范大学闽南科技学院",
      "福建农林大学东方学院",
      "福建农林大学金山学院",
      "福建警察学院",
      "武夷学院",
      "闽南理工学院",
      "泉州医学高等专科学校",
      "福建江夏学院",
      "福州外语外贸学院",
      "华侨大学厦门工学院"
    ]
  },
  "985_211": [
    {
      "university": "厦门大学",
      "is985": true,
      "is211": true
    },
    {
      "university": "福州大学",
      "is985": false,
      "is211": true
    }
  ],
  "normal_schools": [
    {
      "university": "福建师范大学",
      "isNormal": true
    },
    {
      "university": "闽南师范大学",
      "isNormal": true
    },
    {
      "university": "宁德师范学院",
      "isNormal": true
    },
    {
      "university": "福建师范大学协和学院",
      "isNormal": true
    },
    {
      "university": "福建师范大学闽南科技学院",
      "isNormal": true
    }
  ]
},
{
  "_id": {
    "$oid": "67daeb65d560a928cac8dc59"
  },
  "provinces": {
    "province": "河南",
    "universities": [
      "郑州大学",
      "河南工业",
      "河南农大",
      "华北水利水电大学",
      "郑州轻工",
      "郑州航空工业",
      "黄河科技",
      "中原工学院",
      "河南中医学院",
      "河南财经政法",
      "新乡学院",
      "郑州成功财经学院",
      "商丘工学院",
      "河南大学",
      "郑州财经学院",
      "河南科技大学",
      "洛阳师院",
      "安阳工学院",
      "安阳师范学院",
      "南阳理工",
      "南阳师院",
      "河南城建学院",
      "平顶山学院",
      "新乡医学院",
      "河南科技学院",
      "河南师大",
      "信阳师院",
      "商丘师院",
      "河南工商学院",
      "黄淮学院",
      "许昌学院",
      "河南理工",
      "河南工程学院",
      "河南警察学院",
      "洛阳理工学院",
      "信阳农林学院",
      "郑州师范学院",
      "郑州科技学院",
      "河南牧业经济学院",
      "中州大学",
      "郑州升达经贸管理学院",
      "河南科技学院新科学院",
      "河南理工大学万方科技学院",
      "中原工学院信息商务学院",
      "安阳师范学院人文管理学院",
      "商丘学院",
      "河南大学民生学院",
      "河南师范大学新联学院",
      "新乡医学院三全学院",
      "信阳师范学院华锐学院"
    ]
  },
  "985_211": [
    {
      "university": "郑州大学",
      "is985": false,
      "is211": true
    }
  ],
  "normal_schools": [
    {
      "university": "河南师大",
      "isNormal": true
    },
    {
      "university": "洛阳师院",
      "isNormal": true
    },
    {
      "university": "安阳师范学院",
      "isNormal": true
    },
    {
      "university": "南阳师院",
      "isNormal": true
    },
    {
      "university": "信阳师院",
      "isNormal": true
    },
    {
      "university": "商丘师院",
      "isNormal": true
    },
    {
      "university": "河南师范大学新联学院",
      "isNormal": true
    },
    {
      "university": "信阳师范学院华锐学院",
      "isNormal": true
    }
  ]
},
{
  "_id": {
    "$oid": "67daeb6cd560a928cac8dc5b"
  },
  "provinces": {
    "province": "重庆",
    "universities": [
      "重庆大学",
      "西南大学",
      "重庆师大",
      "西南政法",
      "重庆交大",
      "重庆邮电大学",
      "重庆医大",
      "重庆工商",
      "重庆科技学院",
      "重庆理工大学",
      "长江师范学院",
      "四川外国语大学",
      "四川美院",
      "重庆三峡学院",
      "重庆文理",
      "后勤工程学院",
      "重庆工程学院",
      "重庆第二师范学院",
      "重庆大学城市科技学院",
      "重庆人文科技学院",
      "四川外语学院重庆南方翻译学院",
      "重庆师范大学涉外商贸学院",
      "重庆工商大学融智学院",
      "重庆工商大学派斯学院",
      "重庆邮电大学移通学院",
      "西南大学荣昌校区",
      "重庆警察学院",
      "中国人民解放军第三军医大学"
    ]
  },
  "985_211": [
    {
      "university": "重庆大学",
      "is985": true,
      "is211": true
    },
    {
      "university": "西南大学",
      "is985": false,
      "is211": true
    }
  ],
  "normal_schools": [
    {
      "university": "重庆师大",
      "isNormal": true
    },
    {
      "university": "重庆第二师范学院",
      "isNormal": true
    },
    {
      "university": "重庆师范大学涉外商贸学院",
      "isNormal": true
    }
  ]
},
{
  "_id": {
    "$oid": "67daeb74d560a928cac8dc5d"
  },
  "provinces": {
    "province": "云南",
    "universities": [
      "昆明理工大学",
      "云南农大",
      "云南师大",
      "云南财经",
      "云南民大",
      "西南林业大学",
      "昆明医科大学",
      "云南中医学院",
      "红河学院",
      "云南警官学院",
      "云南艺术",
      "云南大学",
      "云南工商学院",
      "大理医学院",
      "昆明理工大学城市学院",
      "曲靖师范",
      "玉溪师院",
      "楚雄师院",
      "大理学院",
      "保山学院",
      "云南大学滇池学院",
      "普洱学院",
      "文山学院",
      "昆明学院",
      "昆明理工大学津桥学院",
      "云南师范大学商学院",
      "云南师范大学文理学院",
      "昆明医学院海源学院",
      "云南艺术学院文华学院",
      "云南大学旅游文化学院"
    ]
  },
  "985_211": [
    {
      "university": "云南大学",
      "is985": false,
      "is211": true
    }
  ],
  "normal_schools": [
    {
      "university": "云南师大",
      "isNormal": true
    },
    {
      "university": "曲靖师范",
      "isNormal": true
    },
    {
      "university": "玉溪师院",
      "isNormal": true
    },
    {
      "university": "楚雄师院",
      "isNormal": true
    },
    {
      "university": "云南师范大学商学院",
      "isNormal": true
    },
    {
      "university": "云南师范大学文理学院",
      "isNormal": true
    }
  ]
},
{
  "_id": {
    "$oid": "67daeb7cd560a928cac8dc5f"
  },
  "provinces": {
    "province": "河北",
    "universities": [
      "河北大学",
      "河北农大",
      "中央司法警官学院",
      "石家庄铁道大学",
      "石家庄经济学院",
      "河北中医学院",
      "河北师大",
      "河北科技大学",
      "河北医科大学",
      "河北经贸大学",
      "河北体育学院",
      "石家庄学院",
      "燕山大学",
      "河北科技师范学院",
      "华北理工大学",
      "唐山学院",
      "唐山师范学院",
      "燕京理工学院",
      "北华航天工业学院",
      "廊坊师范学院",
      "防灾科技学院",
      "华北科技学院",
      "河北建筑工程学院",
      "河北北方学院",
      "承德医学院",
      "邢台学院",
      "河北工程大学",
      "邯郸学院",
      "衡水学院",
      "河北科技学院",
      "河北金融学院",
      "保定学院",
      "沧州师范学院",
      "河北民族师范学院",
      "东北大学秦皇岛校区",
      "河北大学医学部",
      "华北电力大学（保定）",
      "河北美术学院",
      "河北外国语学院",
      "河北传媒学院",
      "河北师范大学汇华学院",
      "河北联合大学冀唐学院",
      "河北医科大学临床学院",
      "河北农业大学现代科技学院",
      "石家庄铁道学院四方学院",
      "燕山大学里仁学院",
      "河北工程大学科信学院",
      "河北联合大学轻工学院",
      "河北大学工商学院",
      "河北经贸大学经济管理学院",
      "北京中医药大学东方学院",
      "石家庄经济学院华信学院"
    ]
  },
  "985_211": [
    {
      "university": "东北大学秦皇岛校区",
      "is985": true,
      "is211": true
    },
    {
      "university": "华北电力大学（保定）",
      "is985": false,
      "is211": true
    }
  ],
  "normal_schools": [
    {
      "university": "河北师大",
      "isNormal": true
    },
    {
      "university": "唐山师范学院",
      "isNormal": true
    },
    {
      "university": "廊坊师范学院",
      "isNormal": true
    },
    {
      "university": "河北科技师范学院",
      "isNormal": true
    },
    {
      "university": "沧州师范学院",
      "isNormal": true
    },
    {
      "university": "河北民族师范学院",
      "isNormal": true
    },
    {
      "university": "河北师范大学汇华学院",
      "isNormal": true
    }
  ]
},
{
  "_id": {
    "$oid": "67daeb84d560a928cac8dc61"
  },
  "provinces": {
    "province": "江西",
    "universities": [
      "江西财经",
      "南昌大学",
      "华东交通大学",
      "南昌航空大学",
      "南昌工程",
      "南昌理工",
      "江西中医药大学",
      "江西科技师范大学",
      "蓝天学院",
      "江西农大",
      "江西师大",
      "江西科技学院",
      "江西理工大学软件学院",
      "东华理工大学",
      "景德镇陶瓷学院",
      "赣南医学院",
      "赣南师范学院",
      "江西理工",
      "上饶师范学院",
      "井冈山大学",
      "宜春学院",
      "九江学院",
      "南昌工学院",
      "南昌师范学院",
      "江西农业大学南昌商学院",
      "江西师范大学科学技术学院",
      "华东交通大学理工学院",
      "江西理工大学应用科学学院",
      "东华理工大学长江学院",
      "南昌航空大学科技学院",
      "江西中医学院科技学院",
      "江西财经大学现代经济管理学院",
      "赣南师范学院科技学院",
      "景德镇陶瓷学院科技艺术学院",
      "江西科技师范学院理工学院",
      "南昌大学共青学院",
      "南昌大学科学技术学院",
      "新余学院"
    ]
  },
  "985_211": [
    {
      "university": "南昌大学",
      "is985": false,
      "is211": true
    }
  ],
  "normal_schools": [
    {
      "university": "江西师大",
      "isNormal": true
    },
    {
      "university": "江西科技师范大学",
      "isNormal": true
    },
    {
      "university": "赣南师范学院",
      "isNormal": true
    },
    {
      "university": "上饶师范学院",
      "isNormal": true
    },
    {
      "university": "江西师范大学科学技术学院",
      "isNormal": true
    },
    {
      "university": "赣南师范学院科技学院",
      "isNormal": true
    },
    {
      "university": "江西科技师范学院理工学院",
      "isNormal": true
    }
  ]
},
{
  "_id": {
    "$oid": "67daeb8bd560a928cac8dc63"
  },
  "provinces": {
    "province": "山西",
    "universities": [
      "山西大学",
      "太原理工",
      "中北大学",
      "山西医大",
      "山西中医学院",
      "太原师范",
      "太原科大",
      "山西财经",
      "太原理工大学现代科技学院",
      "山西师大",
      "山西农大",
      "大同大学",
      "长治医学院",
      "长治学院",
      "运城学院",
      "晋中学院",
      "忻州师范",
      "山西工商学院",
      "太原学院",
      "山西农业大学信息学院",
      "山西医科大学晋祠学院",
      "太原科技大学华科学院",
      "山西财经大学华商学院",
      "中北大学信息商务学院",
      "山西师范大学现代文理学院",
      "山西大学商务学院",
      "太原工业学院",
      "山西传媒学院"
    ]
  },
  "985_211": [
    {
      "university": "太原理工",
      "is985": false,
      "is211": true
    }
  ],
  "normal_schools": [
    {
      "university": "太原师范",
      "isNormal": true
    },
    {
      "university": "山西师大",
      "isNormal": true
    },
    {
      "university": "忻州师范",
      "isNormal": true
    },
    {
      "university": "山西师范大学现代文理学院",
      "isNormal": true
    }
  ]
},
{
  "_id": {
    "$oid": "67daeb93d560a928cac8dc65"
  },
  "provinces": {
    "province": "贵州",
    "universities": [
      "贵州理工学院",
      "贵州大学",
      "贵阳医学院",
      "贵阳中医学院",
      "贵州财经大学",
      "贵州民族大学",
      "贵阳学院",
      "贵州师范大学",
      "铜仁学院",
      "兴义民族师范学院",
      "遵义医学院",
      "遵义师范学院",
      "毕节学院",
      "黔南师院",
      "安顺学院",
      "凯里学院",
      "六盘水师范学院",
      "贵州财经学院商务学院",
      "贵州民族学院人文科技学院",
      "贵州师范大学求是学院",
      "贵阳医学院神奇民族医药学院",
      "遵义医学院医学与科技学院",
      "贵阳中医学院时珍学院",
      "贵州大学明德学院",
      "贵州大学科技学院",
      "贵州师范学院"
    ]
  },
  "985_211": [
    {
      "university": "贵州大学",
      "is985": false,
      "is211": true
    }
  ],
  "normal_schools": [
    {
      "university": "贵州师范大学",
      "isNormal": true
    },
    {
      "university": "兴义民族师范学院",
      "isNormal": true
    },
    {
      "university": "遵义师范学院",
      "isNormal": true
    },
    {
      "university": "毕节学院",
      "isNormal": true
    },
    {
      "university": "黔南师院",
      "isNormal": true
    },
    {
      "university": "贵州师范学院",
      "isNormal": true
    },
    {
      "university": "贵州师范大学求是学院",
      "isNormal": true
    }
  ]
},
{
  "_id": {
    "$oid": "67daeb9bd560a928cac8dc67"
  },
  "provinces": {
    "province": "广西",
    "universities": [
      "广西大学",
      "广西医科大学",
      "广西民族大学",
      "广西中医药大学",
      "广西师范学院",
      "广西财经学院",
      "广西艺术学院",
      "广西外国语学院",
      "桂林电子科技大学",
      "广西师范大学",
      "桂林理工大学",
      "桂林医学院",
      "广西科技大学",
      "右江民族医学院",
      "百色学院",
      "河池学院",
      "玉林师范学院",
      "钦州学院",
      "贺州学院",
      "梧州学院",
      "广西大学行健文理学院",
      "广西师范大学漓江学院",
      "桂林电子科技大学信息科技学院",
      "桂林工学院博文管理学院",
      "广西科技大学鹿山学院",
      "广西师范学院师园学院",
      "广西民族大学相思湖学院",
      "广西中医学院赛恩斯新医药学院",
      "南宁学院",
      "桂林航天工业学院",
      "广西民族师范学院"
    ]
  },
  "985_211": [
    {
      "university": "广西大学",
      "is985": false,
      "is211": true
    }
  ],
  "normal_schools": [
    {
      "university": "广西师范学院",
      "isNormal": true
    },
    {
      "university": "广西师范大学",
      "isNormal": true
    },
    {
      "university": "玉林师范学院",
      "isNormal": true
    },
    {
      "university": "广西师范大学漓江学院",
      "isNormal": true
    },
    {
      "university": "广西师范学院师园学院",
      "isNormal": true
    }
  ]
},
{
  "_id": {
    "$oid": "67daeba3d560a928cac8dc69"
  },
  "provinces": {
    "province": "内蒙古",
    "universities": [
      "内蒙古大学",
      "内蒙古工业大学",
      "内蒙古农大",
      "内蒙古师大",
      "内蒙古医科大学",
      "内蒙古财经大学",
      "内蒙古大学创业学院",
      "内蒙古科技大学包头医学院",
      "内蒙古师范大学鸿德学院",
      "内蒙古大学鄂尔多斯学院",
      "内蒙古大学满洲里学院",
      "内蒙古科大",
      "内蒙古民族大学",
      "赤峰学院",
      "呼伦贝尔学院",
      "呼和浩特民族学院",
      "集宁师范学院",
      "包头师范学院",
      "内蒙古科技大学包头师范学院"
    ]
  },
  "985_211": [
    {
      "university": "内蒙古大学",
      "is985": false,
      "is211": true
    }
  ],
  "normal_schools": [
    {
      "university": "内蒙古师大",
      "isNormal": true
    },
    {
      "university": "包头师范学院",
      "isNormal": true
    },
    {
      "university": "集宁师范学院",
      "isNormal": true
    },
    {
      "university": "内蒙古师范大学鸿德学院",
      "isNormal": true
    },
    {
      "university": "内蒙古科技大学包头师范学院",
      "isNormal": true
    }
  ]
},
{
  "_id": {
    "$oid": "67daebacd560a928cac8dc6b"
  },
  "provinces": {
    "province": "宁夏",
    "universities": [
      "宁夏大学",
      "北方民大",
      "宁夏医科大学",
      "银川能源学院",
      "宁夏理工",
      "宁夏师范学院",
      "宁夏大学新华学院",
      "中国矿业大学银川学院"
    ]
  },
  "985_211": [
    {
      "university": "宁夏大学",
      "is985": false,
      "is211": true
    }
  ],
  "normal_schools": [
    {
      "university": "宁夏师范学院",
      "isNormal": true
    }
  ]
},
{
  "_id": {
    "$oid": "67daebb3d560a928cac8dc6d"
  },
  "provinces": {
    "province": "青海",
    "universities": [
      "青海大学",
      "青海师大",
      "青海民大",
      "青海大学昆仑学院"
    ]
  },
  "985_211": [
    {
      "university": "青海大学",
      "is985": false,
      "is211": true
    }
  ],
  "normal_schools": [
    {
      "university": "青海师大",
      "isNormal": true
    }
  ]
},
{
  "_id": {
    "$oid": "67daebbcd560a928cac8dc6f"
  },
  "provinces": {
    "province": "新疆",
    "universities": [
      "新疆大学",
      "新疆农大",
      "新疆医科大",
      "新疆师大",
      "新疆财经",
      "新疆艺术学院",
      "新疆工程学院",
      "新疆师范大学",
      "石河子大学",
      "塔里木大学",
      "喀什师院",
      "伊犁师院",
      "昌吉学院",
      "新疆大学科学技术学院",
      "新疆农业大学科学技术学院",
      "新疆财经大学商务学院",
      "新疆医科大学厚博学院",
      "石河子大学科技学院",
      "新疆政法学院"
    ]
  },
  "985_211": [
    {
      "university": "新疆大学",
      "is985": false,
      "is211": true
    },
    {
      "university": "石河子大学",
      "is985": false,
      "is211": true
    }
  ],
  "normal_schools": [
    {
      "university": "新疆师大",
      "isNormal": true
    },
    {
      "university": "新疆师范大学",
      "isNormal": true
    },
    {
      "university": "喀什师院",
      "isNormal": true
    },
    {
      "university": "伊犁师院",
      "isNormal": true
    }
  ]
},
{
  "_id": {
    "$oid": "67daebc2d560a928cac8dc71"
  },
  "provinces": {
    "province": "海南",
    "universities": [
      "海南大学",
      "海南医学院",
      "海南师范大学",
      "华南热带农大",
      "琼州学院",
      "海口经济学院",
      "三亚学院",
      "海南科技职业学院"
    ]
  },
  "985_211": [
    {
      "university": "海南大学",
      "is985": false,
      "is211": true
    }
  ],
  "normal_schools": [
    {
      "university": "海南师范大学",
      "isNormal": true
    }
  ]
},
{
  "_id": {
    "$oid": "67daebcad560a928cac8dc73"
  },
  "provinces": {
    "province": "西藏",
    "universities": [
      "西藏大学",
      "西藏藏医学院",
      "西藏民院",
      "西藏民族学院"
    ]
  },
  "985_211": [
    {
      "university": "西藏大学",
      "is985": false,
      "is211": true
    }
  ],
  "normal_schools": []
}]